{
  "id": 494,
  "image_file": "000494.png",
  "text": "Go to the Red Circle",
  "path": [
    [
      64.0,
      64.0
    ],
    [
      61.666666666666664,
      66.88888888888889
    ],
    [
      59.333333333333336,
      69.77777777777777
    ],
    [
      57.0,
      72.66666666666667
    ],
    [
      54.66666666666667,
      75.55555555555556
    ],
    [
      52.33333333333333,
      78.44444444444444
    ],
    [
      50.0,
      81.33333333333333
    ],
    [
      47.66666666666667,
      84.22222222222223
    ],
    [
      45.333333333333336,
      87.11111111111111
    ],
    [
      43.0,
      90.0
    ]
  ],
  "target": {
    "shape": "Circle",
    "color": "Red",
    "position": [
      43,
      90
    ]
  }
}